kinto_emailer/__init__.py
kinto_emailer/command_send.py
kinto_emailer-3.0.3.dist-info/LICENSE
kinto_emailer-3.0.3.dist-info/METADATA
kinto_emailer-3.0.3.dist-info/WHEEL
kinto_emailer-3.0.3.dist-info/entry_points.txt
kinto_emailer-3.0.3.dist-info/top_level.txt
kinto_emailer-3.0.3.dist-info/RECORD
