Metadata-Version: 2.2
Name: kinto-emailer
Version: 3.0.3
Summary: Kinto emailer plugin
Author-email: Mozilla Services <developers@kinto-storage.org>
License: Copyright 2017 - Mozilla Corporation
Project-URL: Repository, https://github.com/Kinto/kinto-emailer
Keywords: web services
Classifier: Programming Language :: Python
Classifier: Programming Language :: Python :: 3
Classifier: Topic :: Internet :: WWW/HTTP
Classifier: Topic :: Internet :: WWW/HTTP :: WSGI :: Application
Classifier: License :: OSI Approved :: Apache Software License
License-File: LICENSE
Requires-Dist: kinto
Requires-Dist: pyramid_mailer
Provides-Extra: dev
Requires-Dist: ruff; extra == "dev"
Requires-Dist: kinto[postgresql]; extra == "dev"
Requires-Dist: kinto-client; extra == "dev"
Requires-Dist: kinto-signer; extra == "dev"
Requires-Dist: mock; extra == "dev"
Requires-Dist: pytest; extra == "dev"
Requires-Dist: pytest-cache; extra == "dev"
Requires-Dist: pytest-cov; extra == "dev"
Requires-Dist: webtest; extra == "dev"
